spencer/__init__.py
spencer-0.0.1.dist-info/DESCRIPTION.rst
spencer-0.0.1.dist-info/METADATA
spencer-0.0.1.dist-info/RECORD
spencer-0.0.1.dist-info/WHEEL
spencer-0.0.1.dist-info/entry_points.txt
spencer-0.0.1.dist-info/metadata.json
spencer-0.0.1.dist-info/top_level.txt
