Metadata-Version: 2.0
Name: spencer
Version: 0.0.1
Summary: Spencer is a frontend to show bud task run results.
Home-page: https://github.com/hoffmann/spencer
Author: Peter Hoffmann
Author-email: ph@peter-hoffmann.com
License: BSD
Platform: UNKNOWN
Classifier: Programming Language :: Python
